fplot/__init__.py
fplot/fplot.py
fplot/pleasy.py
fplot-0.2.4.dist-info/LICENSE.txt
fplot-0.2.4.dist-info/METADATA
fplot-0.2.4.dist-info/WHEEL
fplot-0.2.4.dist-info/top_level.txt
fplot-0.2.4.dist-info/RECORD
