Metadata-Version: 2.1
Name: fplot
Version: 0.2.4
Summary: Plot functions with simple syntax
Home-page: https://github.com/David-OConnor/fplot
Author: David O'Connor
Author-email: david.alan.oconnor@gmail.com
License: Apache 2.0
Keywords: plot,matplotlib,plotting,functions,jupyter
License-File: LICENSE.txt
Requires-Dist: numpy
Requires-Dist: matplotlib
